mesaPlot/__init__.py
mesaPlot/debug.py
mesaPlot/file_reader.py
mesaPlot/plot.py
mesaPlot/version.py
mesaPlot-2.0.11.dist-info/COPYING.txt
mesaPlot-2.0.11.dist-info/METADATA
mesaPlot-2.0.11.dist-info/WHEEL
mesaPlot-2.0.11.dist-info/top_level.txt
mesaPlot-2.0.11.dist-info/RECORD
